dikt/__init__.py
dikt-2.0.0.dist-info/LICENSE
dikt-2.0.0.dist-info/METADATA
dikt-2.0.0.dist-info/WHEEL
dikt-2.0.0.dist-info/top_level.txt
dikt-2.0.0.dist-info/RECORD
