Metadata-Version: 2.1
Name: dikt
Version: 2.0.0
Summary: Dictionary read on disk
Home-page: https://github.com/kerighan/dikt
Author: Maixent Chenebaux
Author-email: max.chbx@gmail.com
License: UNKNOWN
Platform: UNKNOWN
Classifier: Programming Language :: Python :: 3
Classifier: Programming Language :: Python :: 3.7
Classifier: License :: OSI Approved :: MIT License
Classifier: Operating System :: OS Independent
Requires-Python: >=3.5
Requires-Dist: tqdm
Requires-Dist: numpy
